{
    "description": "A condition for conditional text.",
    "elements": {
        "class": {
            "properties": []
        },
        "instance": {
            "properties": [
                {
                    "description": "The unique ID of the Condition.",
                    "type": "number",
                    "array": false,
                    "name": "id",
                    "readonly": true
                },
                {
                    "description": "Returns true if the object specifier resolves to valid objects.",
                    "type": "bool",
                    "array": false,
                    "name": "isValid",
                    "readonly": true
                },
                {
                    "description": "The parent of the Condition (a Application or Document).",
                    "type": "varies=any",
                    "array": false,
                    "name": "parent",
                    "readonly": true
                },
                {
                    "description": "The index of the Condition within its containing object.",
                    "type": "number",
                    "array": false,
                    "name": "index",
                    "readonly": true
                },
                {
                    "description": "A collection of events.",
                    "type": "Events",
                    "array": false,
                    "name": "events",
                    "readonly": true
                },
                {
                    "description": "A collection of event listeners.",
                    "type": "EventListeners",
                    "array": false,
                    "name": "eventListeners",
                    "readonly": true
                },
                {
                    "description": "The name of the Condition.",
                    "type": "string",
                    "array": false,
                    "name": "name",
                    "readonly": false
                },
                {
                    "description": "The color for the condition indicator; specified either as an array of three doubles representing RGB values in the range 0 to 255, or as a UI color. Can return: Array of 3 Reals (0 - 255) or UIColors enumerator.",
                    "type": "varies=any",
                    "array": false,
                    "name": "indicatorColor",
                    "readonly": false
                },
                {
                    "description": "The condition indicator method.",
                    "type": "ConditionIndicatorMethod",
                    "array": false,
                    "name": "indicatorMethod",
                    "readonly": false
                },
                {
                    "description": "The condition underline indicator appearance.",
                    "type": "ConditionUnderlineIndicatorAppearance",
                    "array": false,
                    "name": "underlineIndicatorAppearance",
                    "readonly": false
                },
                {
                    "description": "If true, the Condition is visible.",
                    "type": "bool",
                    "array": false,
                    "name": "visible",
                    "readonly": false
                },
                {
                    "description": "A property that can be set to any string.",
                    "type": "string",
                    "array": false,
                    "name": "label",
                    "readonly": false
                },
                {
                    "description": "A property that allows setting of several properties at the same time.",
                    "type": "Object",
                    "array": false,
                    "name": "properties",
                    "readonly": false
                }
            ],
            "methods": [
                {
                    "description": "Delete the condition.",
                    "parameters": [
                        {
                            "description": "The condition to apply to text in place of the deleted condition. By default, no condition is applied in place of the deleted condition. Can accept: Condition or String. (Optional)",
                            "type": "varies=any",
                            "optional": false,
                            "name": "replacingWith",
                            "array": false
                        }
                    ],
                    "name": "remove"
                },
                {
                    "description": "Sets the label to the value associated with the specified key.",
                    "parameters": [
                        {
                            "description": "The key.",
                            "type": "string",
                            "optional": false,
                            "name": "key",
                            "array": false
                        },
                        {
                            "description": "The value.",
                            "type": "string",
                            "optional": false,
                            "name": "value",
                            "array": false
                        }
                    ],
                    "name": "insertLabel"
                },
                {
                    "description": "Gets the label value associated with the specified key.",
                    "type": "string",
                    "parameters": [
                        {
                            "description": "The key.",
                            "type": "string",
                            "optional": false,
                            "name": "key",
                            "array": false
                        }
                    ],
                    "name": "extractLabel",
                    "array": false
                },
                {
                    "description": "Generates a string which, if executed, will return the Condition.",
                    "type": "string",
                    "parameters": [],
                    "name": "toSource",
                    "array": false
                },
                {
                    "description": "Resolves the object specifier, creating an array of object references.",
                    "type": "Condition",
                    "parameters": [],
                    "name": "getElements",
                    "array": true
                },
                {
                    "description": "Retrieves the object specifier.",
                    "type": "string",
                    "parameters": [],
                    "name": "toSpecifier",
                    "array": false
                },
                {
                    "description": "Adds an event listener.",
                    "type": "EventListener",
                    "parameters": [
                        {
                            "description": "The event type.",
                            "type": "string",
                            "optional": false,
                            "name": "eventType",
                            "array": false
                        },
                        {
                            "description": "The event handler. Can accept: File or JavaScript Function.",
                            "type": "varies=any",
                            "optional": false,
                            "name": "handler",
                            "array": false
                        },
                        {
                            "type": "bool",
                            "value": "false",
                            "name": "captures",
                            "optional": true,
                            "description": "This parameter is obsolete. (Optional)",
                            "array": false
                        }
                    ],
                    "name": "addEventListener",
                    "array": false
                },
                {
                    "description": "Removes the event listener.",
                    "type": "bool",
                    "parameters": [
                        {
                            "description": "The registered event type.",
                            "type": "string",
                            "optional": false,
                            "name": "eventType",
                            "array": false
                        },
                        {
                            "description": "The registered event handler. Can accept: File or JavaScript Function.",
                            "type": "varies=any",
                            "optional": false,
                            "name": "handler",
                            "array": false
                        },
                        {
                            "type": "bool",
                            "value": "false",
                            "name": "captures",
                            "optional": true,
                            "description": "This parameter is obsolete. (Optional)",
                            "array": false
                        }
                    ],
                    "name": "removeEventListener",
                    "array": false
                }
            ]
        }
    },
    "dynamic": true,
    "name": "Condition"
}