{
    "description": "Document print ui options",
    "elements": {
        "class": {
            "properties": [
                {
                    "type": "number",
                    "value": "1936748659",
                    "array": false,
                    "description": "Do not show progress bar during printing.",
                    "readonly": true,
                    "name": "SUPPRESS_PRINT_PROGRESS"
                },
                {
                    "type": "number",
                    "value": "1936750450",
                    "array": false,
                    "description": "Do not show warning dialog during printing.",
                    "readonly": true,
                    "name": "SUPPRESS_PRINT_WARNINGS"
                },
                {
                    "type": "number",
                    "value": "1936745575",
                    "array": false,
                    "description": "Do not show print dialog.",
                    "readonly": true,
                    "name": "SUPPRESS_PRINT_DIALOG"
                },
                {
                    "type": "number",
                    "value": "1936089444",
                    "array": false,
                    "description": "Do not show file save dialog during printing.",
                    "readonly": true,
                    "name": "SUPPRESS_FILE_SAVE_DIALOG"
                }
            ]
        },
        "instance": {
            "properties": [],
            "methods": []
        }
    },
    "dynamic": false,
    "name": "DocumentPrintUiOptions"
}