{
    "description": "A collection of goto state behaviors.",
    "elements": {
        "class": {
            "properties": []
        },
        "instance": {
            "properties": [
                {
                    "description": "The number of objects in the collection.",
                    "type": "number",
                    "array": false,
                    "name": "length",
                    "readonly": true
                }
            ],
            "methods": [
                {
                    "description": "Displays the number of elements in the GotoStateBehavior.",
                    "type": "number",
                    "parameters": [],
                    "name": "count",
                    "array": false
                },
                {
                    "description": "Creates a new GotoStateBehavior.",
                    "type": "GotoStateBehavior",
                    "parameters": [
                        {
                            "description": "Initial values for properties of the new GotoStateBehavior (Optional)",
                            "type": "Object",
                            "optional": false,
                            "name": "withProperties",
                            "array": false
                        }
                    ],
                    "name": "add",
                    "array": false
                },
                {
                    "description": "Returns the GotoStateBehavior with the specified index or name.",
                    "type": "GotoStateBehavior",
                    "parameters": [
                        {
                            "description": "The index or name. Can accept: Long Integer or String.",
                            "type": "varies=any",
                            "optional": false,
                            "name": "index",
                            "array": false
                        }
                    ],
                    "name": "item",
                    "array": false
                },
                {
                    "description": "Returns the GotoStateBehavior with the specified name.",
                    "type": "GotoStateBehavior",
                    "parameters": [
                        {
                            "description": "The name.",
                            "type": "string",
                            "optional": false,
                            "name": "name",
                            "array": false
                        }
                    ],
                    "name": "itemByName",
                    "array": false
                },
                {
                    "description": "Returns the GotoStateBehavior with the specified ID.",
                    "type": "GotoStateBehavior",
                    "parameters": [
                        {
                            "description": "The ID.",
                            "type": "number",
                            "optional": false,
                            "name": "id",
                            "array": false
                        }
                    ],
                    "name": "itemByID",
                    "array": false
                },
                {
                    "description": "Returns the GotoStateBehaviors within the specified range.",
                    "type": "GotoStateBehavior",
                    "parameters": [
                        {
                            "description": "The GotoStateBehavior, index, or name at the beginning of the range. Can accept: GotoStateBehavior, Long Integer or String.",
                            "type": "varies=any",
                            "optional": false,
                            "name": "from",
                            "array": false
                        },
                        {
                            "description": "The GotoStateBehavior, index, or name at the end of the range. Can accept: GotoStateBehavior, Long Integer or String.",
                            "type": "varies=any",
                            "optional": false,
                            "name": "to",
                            "array": false
                        }
                    ],
                    "name": "itemByRange",
                    "array": true
                },
                {
                    "description": "Returns the first GotoStateBehavior in the collection.",
                    "type": "GotoStateBehavior",
                    "parameters": [],
                    "name": "firstItem",
                    "array": false
                },
                {
                    "description": "Returns the last GotoStateBehavior in the collection.",
                    "type": "GotoStateBehavior",
                    "parameters": [],
                    "name": "lastItem",
                    "array": false
                },
                {
                    "description": "Returns the middle GotoStateBehavior in the collection.",
                    "type": "GotoStateBehavior",
                    "parameters": [],
                    "name": "middleItem",
                    "array": false
                },
                {
                    "description": "Returns the GotoStateBehavior with the index previous to the specified index.",
                    "type": "GotoStateBehavior",
                    "parameters": [
                        {
                            "description": "The index of the GotoStateBehavior that follows the desired GotoStateBehavior.",
                            "type": "GotoStateBehavior",
                            "optional": false,
                            "name": "obj",
                            "array": false
                        }
                    ],
                    "name": "previousItem",
                    "array": false
                },
                {
                    "description": "Returns the GotoStateBehavior whose index follows the specified GotoStateBehavior in the collection.",
                    "type": "GotoStateBehavior",
                    "parameters": [
                        {
                            "description": "The GotoStateBehavior whose index comes before the desired GotoStateBehavior.",
                            "type": "GotoStateBehavior",
                            "optional": false,
                            "name": "obj",
                            "array": false
                        }
                    ],
                    "name": "nextItem",
                    "array": false
                },
                {
                    "description": "Returns any GotoStateBehavior in the collection.",
                    "type": "GotoStateBehavior",
                    "parameters": [],
                    "name": "anyItem",
                    "array": false
                },
                {
                    "description": "Returns every GotoStateBehavior in the collection.",
                    "type": "GotoStateBehavior",
                    "parameters": [],
                    "name": "everyItem",
                    "array": true
                },
                {
                    "description": "Generates a string which, if executed, will return the GotoStateBehavior.",
                    "type": "string",
                    "parameters": [],
                    "name": "toSource",
                    "array": false
                },
                {
                    "description": "Returns the GotoStateBehavior with the specified index.",
                    "type": "GotoStateBehavior",
                    "parameters": [
                        {
                            "description": "The index.",
                            "type": "number",
                            "optional": false,
                            "name": "index",
                            "array": false
                        }
                    ],
                    "name": "[]",
                    "array": false
                }
            ]
        }
    },
    "dynamic": true,
    "name": "GotoStateBehaviors"
}