{
    "description": "The page transition direction options.",
    "elements": {
        "class": {
            "properties": [
                {
                    "type": "number",
                    "value": "1886670401",
                    "array": false,
                    "description": "Direction does not apply.",
                    "readonly": true,
                    "name": "NOT_APPLICABLE"
                },
                {
                    "type": "number",
                    "value": "1181971556",
                    "array": false,
                    "description": "The top to bottom direction.",
                    "readonly": true,
                    "name": "DOWN"
                },
                {
                    "type": "number",
                    "value": "1920232546",
                    "array": false,
                    "description": "The right to left direction.",
                    "readonly": true,
                    "name": "RIGHT_TO_LEFT"
                },
                {
                    "type": "number",
                    "value": "1886669892",
                    "array": false,
                    "description": "The down and left direction.",
                    "readonly": true,
                    "name": "LEFT_DOWN"
                },
                {
                    "type": "number",
                    "value": "1886669909",
                    "array": false,
                    "description": "The up and left direction.",
                    "readonly": true,
                    "name": "LEFT_UP"
                },
                {
                    "type": "number",
                    "value": "1819570786",
                    "array": false,
                    "description": "The left to right direction.",
                    "readonly": true,
                    "name": "LEFT_TO_RIGHT"
                },
                {
                    "type": "number",
                    "value": "1886671428",
                    "array": false,
                    "description": "The down and right direction.",
                    "readonly": true,
                    "name": "RIGHT_DOWN"
                },
                {
                    "type": "number",
                    "value": "1886671445",
                    "array": false,
                    "description": "The up and right direction.",
                    "readonly": true,
                    "name": "RIGHT_UP"
                },
                {
                    "type": "number",
                    "value": "1181971566",
                    "array": false,
                    "description": "The bottom to top direction.",
                    "readonly": true,
                    "name": "UP"
                },
                {
                    "type": "number",
                    "value": "1768824864",
                    "array": false,
                    "description": "The inward direction.",
                    "readonly": true,
                    "name": "IN"
                },
                {
                    "type": "number",
                    "value": "1886670708",
                    "array": false,
                    "description": "The outward direction.",
                    "readonly": true,
                    "name": "OUT"
                },
                {
                    "type": "number",
                    "value": "1752134266",
                    "array": false,
                    "description": "The horizontal direction.",
                    "readonly": true,
                    "name": "HORIZONTAL"
                },
                {
                    "type": "number",
                    "value": "1986359924",
                    "array": false,
                    "description": "The vertical direction.",
                    "readonly": true,
                    "name": "VERTICAL"
                },
                {
                    "type": "number",
                    "value": "1886668873",
                    "array": false,
                    "description": "The horizontal inward direction.",
                    "readonly": true,
                    "name": "HORIZONTAL_IN"
                },
                {
                    "type": "number",
                    "value": "1886668879",
                    "array": false,
                    "description": "The horizontal outward direction.",
                    "readonly": true,
                    "name": "HORIZONTAL_OUT"
                },
                {
                    "type": "number",
                    "value": "1886672457",
                    "array": false,
                    "description": "The vertical inward direction.",
                    "readonly": true,
                    "name": "VERTICAL_IN"
                },
                {
                    "type": "number",
                    "value": "1886672463",
                    "array": false,
                    "description": "The vertical outward direction.",
                    "readonly": true,
                    "name": "VERTICAL_OUT"
                }
            ]
        },
        "instance": {
            "properties": [],
            "methods": []
        }
    },
    "dynamic": false,
    "name": "PageTransitionDirectionOptions"
}