{
    "description": "PNG export preferences.",
    "elements": {
        "class": {
            "properties": []
        },
        "instance": {
            "properties": [
                {
                    "description": "Returns true if the object specifier resolves to valid objects.",
                    "type": "bool",
                    "array": false,
                    "name": "isValid",
                    "readonly": true
                },
                {
                    "description": "The parent of the PNGExportPreference (a Application).",
                    "type": "Application",
                    "array": false,
                    "name": "parent",
                    "readonly": true
                },
                {
                    "description": "A collection of events.",
                    "type": "Events",
                    "array": false,
                    "name": "events",
                    "readonly": true
                },
                {
                    "description": "A collection of event listeners.",
                    "type": "EventListeners",
                    "array": false,
                    "name": "eventListeners",
                    "readonly": true
                },
                {
                    "description": "The page range to export.",
                    "type": "PNGExportRangeEnum",
                    "array": false,
                    "name": "pngExportRange",
                    "readonly": false
                },
                {
                    "description": "The page(s) to export, specified as a page number or an array of page numbers. Note: Valid when PNG export range is not all.",
                    "type": "string",
                    "array": false,
                    "name": "pageString",
                    "readonly": false
                },
                {
                    "description": "If true, exports each spread as a single PNG file. If false, exports facing pages as separate files and appends sequential numbers to each file name.",
                    "type": "bool",
                    "array": false,
                    "name": "exportingSpread",
                    "readonly": false
                },
                {
                    "description": "The compression quality.",
                    "type": "PNGQualityEnum",
                    "array": false,
                    "name": "pngQuality",
                    "readonly": false
                },
                {
                    "description": "The export resolution expressed as a real number instead of an integer. (Range: 1.0 to 2400.0)",
                    "type": "number",
                    "array": false,
                    "name": "exportResolution",
                    "readonly": false
                },
                {
                    "description": "RGB or Gray",
                    "type": "PNGColorSpaceEnum",
                    "array": false,
                    "name": "pngColorSpace",
                    "readonly": false
                },
                {
                    "description": "If true, use a transparent background for the exported PNG.",
                    "type": "bool",
                    "array": false,
                    "name": "transparentBackground",
                    "readonly": false
                },
                {
                    "description": "If true, use anti-aliasing for text and vectors during export.",
                    "type": "bool",
                    "array": false,
                    "name": "antiAlias",
                    "readonly": false
                },
                {
                    "description": "If true, uses the document's bleed settings in the exported PNG.",
                    "type": "bool",
                    "array": false,
                    "name": "useDocumentBleeds",
                    "readonly": false
                },
                {
                    "description": "If true, simulates the effects of overprinting spot and process colors in the same way they would occur when printing.",
                    "type": "bool",
                    "array": false,
                    "name": "simulateOverprint",
                    "readonly": false
                },
                {
                    "description": "A property that allows setting of several properties at the same time.",
                    "type": "Object",
                    "array": false,
                    "name": "properties",
                    "readonly": false
                }
            ],
            "methods": [
                {
                    "description": "Generates a string which, if executed, will return the PNGExportPreference.",
                    "type": "string",
                    "parameters": [],
                    "name": "toSource",
                    "array": false
                },
                {
                    "description": "Resolves the object specifier, creating an array of object references.",
                    "type": "PNGExportPreference",
                    "parameters": [],
                    "name": "getElements",
                    "array": true
                },
                {
                    "description": "Retrieves the object specifier.",
                    "type": "string",
                    "parameters": [],
                    "name": "toSpecifier",
                    "array": false
                },
                {
                    "description": "Adds an event listener.",
                    "type": "EventListener",
                    "parameters": [
                        {
                            "description": "The event type.",
                            "type": "string",
                            "optional": false,
                            "name": "eventType",
                            "array": false
                        },
                        {
                            "description": "The event handler. Can accept: File or JavaScript Function.",
                            "type": "varies=any",
                            "optional": false,
                            "name": "handler",
                            "array": false
                        },
                        {
                            "type": "bool",
                            "value": "false",
                            "name": "captures",
                            "optional": true,
                            "description": "This parameter is obsolete. (Optional)",
                            "array": false
                        }
                    ],
                    "name": "addEventListener",
                    "array": false
                },
                {
                    "description": "Removes the event listener.",
                    "type": "bool",
                    "parameters": [
                        {
                            "description": "The registered event type.",
                            "type": "string",
                            "optional": false,
                            "name": "eventType",
                            "array": false
                        },
                        {
                            "description": "The registered event handler. Can accept: File or JavaScript Function.",
                            "type": "varies=any",
                            "optional": false,
                            "name": "handler",
                            "array": false
                        },
                        {
                            "type": "bool",
                            "value": "false",
                            "name": "captures",
                            "optional": true,
                            "description": "This parameter is obsolete. (Optional)",
                            "array": false
                        }
                    ],
                    "name": "removeEventListener",
                    "array": false
                }
            ]
        }
    },
    "dynamic": true,
    "name": "PNGExportPreference"
}