{
    "description": "Timing settings.",
    "elements": {
        "class": {
            "properties": []
        },
        "instance": {
            "properties": [
                {
                    "description": "Dynamic targets on the spread that are not assigned.",
                    "type": "Object",
                    "array": true,
                    "name": "unassignedDynamicTargets",
                    "readonly": true
                },
                {
                    "description": "Returns true if the object specifier resolves to valid objects.",
                    "type": "bool",
                    "array": false,
                    "name": "isValid",
                    "readonly": true
                },
                {
                    "description": "The parent of the TimingSetting (a PageItem, HtmlItem, FormField, SignatureField, TextBox, RadioButton, ListBox, ComboBox, CheckBox, MultiStateObject, Button, MediaItem, Sound, Movie, EPSText, SplineItem, Polygon, GraphicLine, Rectangle, Oval, Graphic, ImportedPage, PICT, WMF, PDF, EPS, Image, Group, TextFrame, MasterSpread or Spread).",
                    "type": "varies=any",
                    "array": false,
                    "name": "parent",
                    "readonly": true
                },
                {
                    "description": "A collection of events.",
                    "type": "Events",
                    "array": false,
                    "name": "events",
                    "readonly": true
                },
                {
                    "description": "A collection of event listeners.",
                    "type": "EventListeners",
                    "array": false,
                    "name": "eventListeners",
                    "readonly": true
                },
                {
                    "description": "A collection of timing lists.",
                    "type": "TimingLists",
                    "array": false,
                    "name": "timingLists",
                    "readonly": true
                },
                {
                    "description": "A property that allows setting of several properties at the same time.",
                    "type": "Object",
                    "array": false,
                    "name": "properties",
                    "readonly": false
                }
            ],
            "methods": [
                {
                    "description": "Generates a string which, if executed, will return the TimingSetting.",
                    "type": "string",
                    "parameters": [],
                    "name": "toSource",
                    "array": false
                },
                {
                    "description": "Resolves the object specifier, creating an array of object references.",
                    "type": "TimingSetting",
                    "parameters": [],
                    "name": "getElements",
                    "array": true
                },
                {
                    "description": "Retrieves the object specifier.",
                    "type": "string",
                    "parameters": [],
                    "name": "toSpecifier",
                    "array": false
                },
                {
                    "description": "Adds an event listener.",
                    "type": "EventListener",
                    "parameters": [
                        {
                            "description": "The event type.",
                            "type": "string",
                            "optional": false,
                            "name": "eventType",
                            "array": false
                        },
                        {
                            "description": "The event handler. Can accept: File or JavaScript Function.",
                            "type": "varies=any",
                            "optional": false,
                            "name": "handler",
                            "array": false
                        },
                        {
                            "type": "bool",
                            "value": "false",
                            "name": "captures",
                            "optional": true,
                            "description": "This parameter is obsolete. (Optional)",
                            "array": false
                        }
                    ],
                    "name": "addEventListener",
                    "array": false
                },
                {
                    "description": "Removes the event listener.",
                    "type": "bool",
                    "parameters": [
                        {
                            "description": "The registered event type.",
                            "type": "string",
                            "optional": false,
                            "name": "eventType",
                            "array": false
                        },
                        {
                            "description": "The registered event handler. Can accept: File or JavaScript Function.",
                            "type": "varies=any",
                            "optional": false,
                            "name": "handler",
                            "array": false
                        },
                        {
                            "type": "bool",
                            "value": "false",
                            "name": "captures",
                            "optional": true,
                            "description": "This parameter is obsolete. (Optional)",
                            "array": false
                        }
                    ],
                    "name": "removeEventListener",
                    "array": false
                }
            ]
        }
    },
    "dynamic": true,
    "name": "TimingSetting"
}